Metadata-Version: 2.1
Name: gapmap
Version: 1.0.4
Summary: Maptools
Author: Paul Gardiner
Author-email: franticstone@gmail.com
License: MIT
Keywords: radius,point,mathlib
Classifier: Development Status :: 3 - Alpha
Classifier: Intended Audience :: Developers
Classifier: License :: OSI Approved :: MIT License
Classifier: Programming Language :: Python :: 3
License-File: LICENSE
